Metadata-Version: 2.1
Name: force-absolute-imports
Version: 0.11.0
Summary: tiny tool to force absolute imports in python code
Home-page: https://github.com/tandav/force_absolute_imports
Author: Alexander Rodionov
Author-email: tandav@tandav.me
